pygpsparser/__init__.py
pygpsparser/gpsparser.py
tests/NMEA_message_sample.py
tests/__init__.py
tests/test_parser/__init__.py
tests/test_parser/test_parser.py
pygpsparser-0.0.7.dist-info/METADATA
pygpsparser-0.0.7.dist-info/WHEEL
pygpsparser-0.0.7.dist-info/top_level.txt
pygpsparser-0.0.7.dist-info/RECORD
