Metadata-Version: 2.1
Name: pygpsparser
Version: 0.0.7
Summary: GPS Sentence Parser
Home-page: https://github.com/Kun-Neng/py-gps-parser
Author: Kun-Neng Hung
Author-email: kunneng.hung@gmail.com
License: UNKNOWN
Platform: UNKNOWN
Classifier: Programming Language :: Python :: 3
Classifier: License :: OSI Approved :: MIT License
Classifier: Operating System :: OS Independent
Requires-Python: >=3.6
Requires-Dist: pytz
